plumed_bench_pp/__about__.py
plumed_bench_pp/__init__.py
plumed_bench_pp/constants.py
plumed_bench_pp/parser.py
plumed_bench_pp/plot.py
plumed_bench_pp/tabulate.py
plumed_bench_pp/types.py
plumed_bench_pp/utils.py
plumed_bench_pp/cli/__init__.py
plumed_bench_pp-0.0.9.dist-info/METADATA
plumed_bench_pp-0.0.9.dist-info/WHEEL
plumed_bench_pp-0.0.9.dist-info/entry_points.txt
plumed_bench_pp-0.0.9.dist-info/licenses/LICENSE.txt
plumed_bench_pp-0.0.9.dist-info/RECORD
