Metadata-Version: 2.4
Name: plumed-bench-pp
Version: 0.0.9
Summary: A simpe package to rapidly postprocessing the output of plumed benchmarks
Project-URL: Documentation, https://github.com/Iximiel/plumed-bench-pp#readme
Project-URL: Issues, https://github.com/Iximiel/plumed-bench-pp/issues
Project-URL: Source, https://github.com/Iximiel/plumed-bench-pp
Author-email: Daniele Rapetti <daniele.rapetti@sissa.it>
License-Expression: MIT
License-File: LICENSE.txt
Classifier: Development Status :: 4 - Beta
Classifier: Programming Language :: Python
Classifier: Programming Language :: Python :: 3.8
Classifier: Programming Language :: Python :: 3.9
Classifier: Programming Language :: Python :: 3.10
Classifier: Programming Language :: Python :: 3.11
Classifier: Programming Language :: Python :: 3.12
Classifier: Programming Language :: Python :: Implementation :: CPython
Classifier: Programming Language :: Python :: Implementation :: PyPy
Requires-Python: >=3.8
Requires-Dist: click
Requires-Dist: matplotlib
Requires-Dist: pandas
